pypkg_winstonyym/__init__.py
pypkg_winstonyym/data/__init__.py
pypkg_winstonyym/data/zen.txt
pypkg_winstonyym/datasets.py
pypkg_winstonyym/plotting.py
pypkg_winstonyym/pypkg_winstonyym.py
pypkg_winstonyym-0.4.0.dist-info/LICENSE
pypkg_winstonyym-0.4.0.dist-info/WHEEL
pypkg_winstonyym-0.4.0.dist-info/METADATA
pypkg_winstonyym-0.4.0.dist-info/RECORD
