Metadata-Version: 2.1
Name: pypkg-winstonyym
Version: 0.4.0
Summary: testing package build
License: MIT
Author: winstonyym
Requires-Python: >=3.9,<4.0
Classifier: License :: OSI Approved :: MIT License
Classifier: Programming Language :: Python :: 3
Classifier: Programming Language :: Python :: 3.10
Classifier: Programming Language :: Python :: 3.9
Requires-Dist: matplotlib (>=3.5.2)
